masato/__init__.py
masato/analysis.py
masato/analysis_sintax.py
masato/cli.py
masato/diversity.py
masato/get_abundance.py
masato/get_tree.py
masato/io.py
masato/isolate_plot.py
masato/isolate_utils.py
masato/plot.py
masato/plot_dm.py
masato/plot_tree.py
masato/process_nbc_tax.py
masato/process_queue.py
masato/process_rrndb.py
masato/reorder.py
masato/run_rdp_classifier.py
masato/trim.py
masato/usearch_workflow.py
masato/utils.py
masato/utils_blast.py
masato/data/conda_requirements.txt
masato/data/isolate/barcode_layout.tsv
masato/data/isolate/barcodes_fwd.fasta
masato/data/isolate/barcodes_rev.fasta
masato/data/isolate/barcodes_rev_es.fasta
masato/data/isolate/patterns.txt
masato/data/isolate/patterns_mmv.txt
masato/data/maps_seq/BC1.fasta
masato/data/maps_seq/BC2.fasta
masato/data/maps_seq/BC3.fasta
masato/data/rnatag_seq/barcode.fasta
masato/plots/__init__.py
masato/plots/dm.py
masato/plots/dm_plotly.py
masato/preprocess/__init__.py
masato/preprocess/basic.py
masato/preprocess/camii_isolates.py
masato/preprocess/main.py
masato/preprocess/maps_seq.py
masato/preprocess/rnatag_seq.py
masato/read_processer/map_utils.py
masato/read_processer/recording.py
masato/setup/conda_install.py
masato/setup/download_rdp.py
masato/setup/download_test_data.py
masato/setup/info.yaml
masato-1.6.0.dist-info/METADATA
masato-1.6.0.dist-info/WHEEL
masato-1.6.0.dist-info/entry_points.txt
masato-1.6.0.dist-info/RECORD
